nkchanger.py
nkchanger-0.1.dist-info/LICENSE
nkchanger-0.1.dist-info/METADATA
nkchanger-0.1.dist-info/WHEEL
nkchanger-0.1.dist-info/top_level.txt
nkchanger-0.1.dist-info/RECORD
